smartpassgen/__init__.py
smartpassgen/generators.py
smartpassgen-0.4.0.dist-info/LICENSE
smartpassgen-0.4.0.dist-info/METADATA
smartpassgen-0.4.0.dist-info/WHEEL
smartpassgen-0.4.0.dist-info/top_level.txt
smartpassgen-0.4.0.dist-info/RECORD
