Metadata-Version: 2.1
Name: smartpassgen
Version: 0.4.0
Summary: A cross-platform package of modules for generating complex, smart, generated and recoverable passwords "on the fly", linked to a login and a secret phrase.
Home-page: https://github.com/smartlegionlab/smartpassgen/
Author: A.A Suvorov
Author-email: smartlegiondev@gmail.com
License: BSD 3-Clause License
Project-URL: Documentation, https://github.com/smartlegionlab/smartpassgen/blob/master/README.md
Project-URL: Release notes, https://github.com/smartlegionlab/smartpassgen/releases
Keywords: password generator,smartpassgen,smartlegionlab,smart password generators,smart password,recoverable password
Platform: UNKNOWN
Classifier: Development Status :: 5 - Production/Stable
Classifier: License :: OSI Approved :: BSD License
Classifier: Natural Language :: English
Classifier: Operating System :: OS Independent
Classifier: Operating System :: Microsoft :: Windows
Classifier: Operating System :: POSIX :: Linux
Classifier: Programming Language :: Python :: 3 :: Only
Classifier: Topic :: Software Development :: Libraries :: Python Modules
Requires-Python: >=3.6
License-File: LICENSE
